metorial_util_endpoint/__init__.py
metorial_util_endpoint/base_endpoint.py
metorial_util_endpoint/endpoint_manager.py
metorial_util_endpoint/request.py
metorial_util_endpoint-1.0.3.dist-info/METADATA
metorial_util_endpoint-1.0.3.dist-info/WHEEL
metorial_util_endpoint-1.0.3.dist-info/licenses/LICENSE
metorial_util_endpoint-1.0.3.dist-info/RECORD
