Metadata-Version: 2.4
Name: metorial-util-endpoint
Version: 1.0.3
Summary: HTTP endpoint utilities for Metorial
Project-URL: Homepage, https://metorial.com
Project-URL: Documentation, https://metorial.com/docs
Project-URL: Repository, https://github.com/metorial/metorial-python
Author-email: Metorial Team <support@metorial.com>
License: MIT
License-File: LICENSE
Keywords: endpoint,http,metorial
Classifier: Development Status :: 4 - Beta
Classifier: Intended Audience :: Developers
Classifier: Programming Language :: Python :: 3
Classifier: Programming Language :: Python :: 3.8
Classifier: Programming Language :: Python :: 3.9
Classifier: Programming Language :: Python :: 3.10
Classifier: Programming Language :: Python :: 3.11
Classifier: Programming Language :: Python :: 3.12
Classifier: Topic :: Software Development :: Libraries :: Python Modules
Requires-Python: >=3.9
Requires-Dist: aiohttp>=3.8.0
Requires-Dist: metorial-exceptions>=1.0.0
Requires-Dist: requests>=2.25.0
Requires-Dist: truststore>=0.8.0
Requires-Dist: typing-extensions>=4.0.0
